Metadata-Version: 1.0
Name: libmaker
Version: 0.1
Summary: A library that makes making libraries and uploading them to pypi easy
Home-page: UNKNOWN
Author: UNKNOWN
Author-email: UNKNOWN
License: UNKNOWN
Keywords: library create make easy
Platform: UNKNOWN
